{"GlobalPropertiesHash":"9mm7tthdurlwlSt+F04ik3mSoW48pMBz6/C1VNdC6/c=","FingerprintPatternsHash":"gq3WsqcKBUGTSNle7RKKyXRIwh7M8ccEqOqYvIzoM04=","PropertyOverridesHash":"8ZRc1sGeVrPBx4lD717BgRaQekyh78QKV9SKsdt638U=","InputHashes":["5xsYZ5QvJHzrqegd6nO/unSI96C4iGr\u002Bs\u002BE7IbPr9hQ=","\u002BJ98UdTKew0vkZEvGLM71P\u002BbgcbHJ9rDfnmIrgDauSw=","ACL2K5iVan1qzF36HvqM36alsn\u002Bej\u002Bdj40Ox4Xpp4dM=","erVKX50yB411FroeVWYrvahjTIaSHVEeNZkpwSn9/mc=","Y/epcpNo5z\u002BnjTNIAX3gs45AdgGMCSNlSfbn9cHCf38=","HzmevfllPtgzfCnJbdtTGeZm8UptF81jwpRFbiGq4IQ=","lke47HMXX7bjdW9GMppsfUormii5h\u002Bf4qLCmJkCG18k=","OES10KK0LO8fvOJ9Sa/1bUkH7rZvTRbIMhG2RbYWCd0=","5a6KNM1RRzfubm1xUYYgOLTPZQeq5e3AEl6apqSM3MA=","CQY/lJ8t/MWtrCQPMYp3NFJvOM8mOVB4U/Adk0BrdPs=","lXNaQIEL3J9/vxYCN7kzNIhAAt9p63HVhJnkl2O/2uA=","Q2I8Dp/Dbury07OSyF7tizC9Ikn2jegmEQuRz6VXJbo=","i3wg/LwDt9TMKuL3Jlu/YneEguDLCJvzWG27/0/OnnQ=","KnG0O1o3jQii8Yxh74brCRrIAvXwq0vwTaUO8HDJHfA=","YImagb/gntY9o1LrxHKa0kKNJLT5\u002BFqGKg3wxsDHCDY=","lJ7XjMq0S7fYXD/S54JG2l\u002BvJebtPkGvkhBP6sNUdrY=","9ITIIg7Zbtm4szzcf\u002BcZ4bpYvE8qwaIb05opmcJ3t30=","TxPC4ZnlUFhLscVQEYiMDthTuQBXF9XQmyksAf/3Gs4=","sg5I4eNrhgOs\u002BbtzsJf9Rm72kFSfI/jvo8QsGgieYxU=","X\u002BsnBVwDIyLMJ7srWlMz2GqCvGa3jGu4EtJHncUfi9c=","NCF6NrmGu0JPepqFaMn9a5TrfCWd3MwIihbUiXwkVVo="],"CachedAssets":{"5xsYZ5QvJHzrqegd6nO/unSI96C4iGr\u002Bs\u002BE7IbPr9hQ=":{"Identity":"C:\\Users\\Student\\Documents\\GitHub\\Finelytics\\finelytics\\wwwroot\\app.css","SourceId":"finelytics","SourceType":"Discovered","ContentRoot":"C:\\Users\\Student\\Documents\\GitHub\\Finelytics\\finelytics\\wwwroot\\","BasePath":"_content/finelytics","RelativePath":"app#[.{fingerprint}]?.css","AssetKind":"All","AssetMode":"All","AssetRole":"Primary","AssetMergeBehavior":null,"AssetMergeSource":"","RelatedAsset":null,"AssetTraitName":null,"AssetTraitValue":null,"Fingerprint":"h6esqvw4ja","Integrity":"N5MRdszMDS77UONNqrBWTczs8b/WrBB1\u002BmY3YjTy9VI=","CopyToOutputDirectory":"Never","CopyToPublishDirectory":"PreserveNewest","OriginalItemSpec":"wwwroot\\app.css","FileLength":13197,"LastWriteTime":"2025-11-14T13:27:45.793592+00:00"},"\u002BJ98UdTKew0vkZEvGLM71P\u002BbgcbHJ9rDfnmIrgDauSw=":{"Identity":"C:\\Users\\Student\\Documents\\GitHub\\Finelytics\\finelytics\\wwwroot\\chartJsInterop.js","SourceId":"finelytics","SourceType":"Discovered","ContentRoot":"C:\\Users\\Student\\Documents\\GitHub\\Finelytics\\finelytics\\wwwroot\\","BasePath":"_content/finelytics","RelativePath":"chartJsInterop#[.{fingerprint}]?.js","AssetKind":"All","AssetMode":"All","AssetRole":"Primary","AssetMergeBehavior":null,"AssetMergeSource":"","RelatedAsset":null,"AssetTraitName":null,"AssetTraitValue":null,"Fingerprint":"ozea1kqgm9","Integrity":"ZHtLdPIIb8FkMs0anJknCfEnWqYeMTJnFqDswcoijMY=","CopyToOutputDirectory":"Never","CopyToPublishDirectory":"PreserveNewest","OriginalItemSpec":"wwwroot\\chartJsInterop.js","FileLength":4047,"LastWriteTime":"2025-11-14T13:27:45.793592+00:00"}},"CachedCopyCandidates":{}}